cmspubstyle/__init__.py
cmspubstyle/pubcheck.py
cmspubstyle/rules/__init__.py
cmspubstyle/rules/classes.py
cmspubstyle/rules/latex.py
cmspubstyle/rules/normal_text.py
cmspubstyle-0.1.0.data/scripts/pubcheck.py
cmspubstyle-0.1.0.dist-info/METADATA
cmspubstyle-0.1.0.dist-info/RECORD
cmspubstyle-0.1.0.dist-info/WHEEL
cmspubstyle-0.1.0.dist-info/top_level.txt
