Metadata-Version: 2.1
Name: cmspubstyle
Version: 0.1.0
Summary: Check CMS publications against PubComm rules
Home-page: https://github.com/raggleton/cmspubstyle
Author: Robin Aggleton
Author-email: UNKNOWN
License: UNKNOWN
Platform: UNKNOWN
Classifier: License :: OSI Approved :: MIT License 
Classifier: Programming Language :: Python :: 2.7
Classifier: Programming Language :: Python :: 3.5
Classifier: Programming Language :: Python :: 3.6
Classifier: Topic :: Scientific/Engineering :: Physics
Classifier: Topic :: Text Processing
